[
  { "group": ["focus", "discipline", "patience", "growth"] },
  { "group": ["courage", "action", "vision", "belief"] },
  { "group": ["hardwork", "consistency", "success", "effort"] },
  { "group": ["strength", "commitment", "drive", "energy"] },
  { "group": ["leadership", "purpose", "mindset", "clarity"] },
  { "group": ["learning", "improvement", "confidence", "progress"] },
  { "group": ["ambition", "motivation", "dedication", "result"] },
  { "group": ["determination", "focus", "resilience", "achievement"] },
  { "group": ["courage", "faith", "action", "determination"] },
  { "group": ["discipline", "habit", "consistency", "success"] },

  { "group": ["vision", "strategy", "planning", "execution"] },
  { "group": ["confidence", "courage", "effort", "victory"] },
  { "group": ["dream", "plan", "work", "achieve"] },
  { "group": ["focus", "speed", "persistence", "success"] },
  { "group": ["mindset", "goals", "action", "reward"] },
  { "group": ["faith", "strength", "endurance", "progress"] },
  { "group": ["discipline", "respect", "positivity", "energy"] },
  { "group": ["motivation", "courage", "fire", "commitment"] },
  { "group": ["optimism", "effort", "growth", "achievement"] },
  { "group": ["ambition", "hope", "drive", "success"] },

  { "group": ["habit", "focus", "drive", "momentum"] },
  { "group": ["direction", "clarity", "purpose", "success"] },
  { "group": ["initiative", "courage", "power", "outcome"] },
  { "group": ["success", "effort", "mindset", "consistency"] },
  { "group": ["courage", "challenge", "victory", "progress"] },
  { "group": ["commitment", "focus", "sacrifice", "reward"] },
  { "group": ["learning", "growth", "wisdom", "achievement"] },
  { "group": ["ambition", "drive", "effort", "impact"] },
  { "group": ["hope", "belief", "determination", "success"] },
  { "group": ["vision", "mission", "action", "result"] },

  { "group": ["passion", "energy", "effort", "achievement"] },
  { "group": ["improvement", "growth", "focus", "result"] },
  { "group": ["resilience", "strength", "courage", "success"] },
  { "group": ["discipline", "focus", "practice", "mastery"] },
  { "group": ["ambition", "success", "momentum", "courage"] },
  { "group": ["drive", "power", "dedication", "progress"] },
  { "group": ["belief", "faith", "direction", "success"] },
  { "group": ["vision", "focus", "commitment", "achievement"] },
  { "group": ["courage", "work", "focus", "growth"] },
  { "group": ["ambition", "aspire", "achieve", "excel"] },

  { "group": ["challenge", "effort", "strength", "victory"] },
  { "group": ["motivation", "discipline", "achievement", "focus"] },
  { "group": ["positive", "productive", "confident", "strong"] },
  { "group": ["hope", "vision", "effort", "success"] },
  { "group": ["dedication", "effort", "belief", "outcome"] },
  { "group": ["focus", "desire", "drive", "achievement"] },
  { "group": ["courage", "mindset", "goal", "victory"] },
  { "group": ["energy", "movement", "growth", "success"] },
  { "group": ["patience", "strength", "wisdom", "achievement"] },
  { "group": ["discipline", "habit", "growth", "success"] },

  { "group": ["action", "focus", "progress", "achievement"] },
  { "group": ["vision", "effort", "courage", "determination"] },
  { "group": ["motivation", "focus", "practice", "success"] },
  { "group": ["consistency", "growth", "effort", "achievement"] },
  { "group": ["courage", "drive", "success", "momentum"] },
  { "group": ["habit", "action", "focus", "results"] },
  { "group": ["calm", "clarity", "focus", "success"] },
  { "group": ["pressure", "strength", "focus", "achievement"] },
  { "group": ["ambition", "courage", "determination", "victory"] },
  { "group": ["dedication", "effort", "drive", "success"] },

  { "group": ["focus", "power", "mindset", "momentum"] },
  { "group": ["vision", "belief", "drive", "result"] },
  { "group": ["success", "courage", "confidence", "commitment"] },
  { "group": ["growth", "effort", "patience", "achievement"] },
  { "group": ["mindset", "courage", "action", "success"] },
  { "group": ["effort", "focus", "drive", "outcome"] },
  { "group": ["consistency", "effort", "drive", "victory"] },
  { "group": ["purpose", "action", "belief", "success"] },
  { "group": ["dream", "believe", "pursue", "achieve"] },
  { "group": ["ambition", "work", "discipline", "achievement"] },

  { "group": ["focus", "mindset", "habits", "success"] },
  { "group": ["energy", "drive", "movement", "achievement"] },
  { "group": ["discipline", "progress", "habit", "victory"] },
  { "group": ["success", "vision", "plan", "execution"] },
  { "group": ["power", "effort", "commitment", "achievement"] },
  { "group": ["momentum", "drive", "focus", "success"] },
  { "group": ["clarity", "action", "purpose", "achievement"] },
  { "group": ["courage", "belief", "strength", "victory"] },
  { "group": ["ambition", "goal", "movement", "success"] },
  { "group": ["patience", "effort", "discipline", "growth"] },

  { "group": ["focus", "challenge", "strength", "success"] },
  { "group": ["learning", "wisdom", "effort", "achievement"] },
  { "group": ["courage", "drive", "consistency", "reward"] },
  { "group": ["ambition", "motivation", "focus", "result"] },
  { "group": ["belief", "courage", "confidence", "success"] },
  { "group": ["drive", "discipline", "strength", "victory"] },
  { "group": ["smartwork", "effort", "focus", "growth"] },
  { "group": ["mindset", "drive", "focus", "outcome"] },
  { "group": ["dedication", "habit", "effort", "achievement"] },
  { "group": ["courage", "hope", "faith", "success"] }
]
